edoping/__init__.py
edoping/cli.py
edoping/cpot.py
edoping/defect.py
edoping/dft.py
edoping/fermi.py
edoping/misc.py
edoping/query.py
edoping-0.4.3.dist-info/LICENSE
edoping-0.4.3.dist-info/METADATA
edoping-0.4.3.dist-info/WHEEL
edoping-0.4.3.dist-info/entry_points.txt
edoping-0.4.3.dist-info/top_level.txt
edoping-0.4.3.dist-info/RECORD
