Metadata-Version: 2.1
Name: eDoping
Version: 0.4.3
Summary: A high-throughput software package for evaluating point defects
Home-page: https://github.com/JianboHIT/eDoping
Author: Jianbo ZHU, Jingyu LI, Peng-Fei LIU
License: Apache-2.0 license
Classifier: Development Status :: 3 - Alpha
Classifier: Programming Language :: Python :: 3
Classifier: Topic :: Scientific/Engineering
Classifier: Intended Audience :: Science/Research
Classifier: License :: OSI Approved :: Apache Software License
Requires-Python: >=3.8
License-File: LICENSE
Requires-Dist: numpy
Requires-Dist: scipy
